Metadata-Version: 1.0
Name: yoyo-pack
Version: 0.0.1
Summary: yoyo pack
Home-page: UNKNOWN
Author: Yolozh
Author-email: UNKNOWN
License: GPL-3.0
Platform: UNKNOWN
